odoo/addons/hr_personal_equipment_request_tier_validation/README.rst
odoo/addons/hr_personal_equipment_request_tier_validation/__init__.py
odoo/addons/hr_personal_equipment_request_tier_validation/__manifest__.py
odoo/addons/hr_personal_equipment_request_tier_validation/data/tier_definition.xml
odoo/addons/hr_personal_equipment_request_tier_validation/i18n/es.po
odoo/addons/hr_personal_equipment_request_tier_validation/i18n/es_PA.po
odoo/addons/hr_personal_equipment_request_tier_validation/i18n/hr_personal_equipment_request_tier_validation.pot
odoo/addons/hr_personal_equipment_request_tier_validation/i18n/it.po
odoo/addons/hr_personal_equipment_request_tier_validation/i18n/pt_BR.po
odoo/addons/hr_personal_equipment_request_tier_validation/models/__init__.py
odoo/addons/hr_personal_equipment_request_tier_validation/models/hr_personal_equipment_request.py
odoo/addons/hr_personal_equipment_request_tier_validation/models/tier_definition.py
odoo/addons/hr_personal_equipment_request_tier_validation/readme/CONTRIBUTORS.rst
odoo/addons/hr_personal_equipment_request_tier_validation/readme/DESCRIPTION.rst
odoo/addons/hr_personal_equipment_request_tier_validation/static/description/icon.png
odoo/addons/hr_personal_equipment_request_tier_validation/static/description/index.html
odoo14_addon_hr_personal_equipment_request_tier_validation-14.0.1.0.1.dist-info/METADATA
odoo14_addon_hr_personal_equipment_request_tier_validation-14.0.1.0.1.dist-info/WHEEL
odoo14_addon_hr_personal_equipment_request_tier_validation-14.0.1.0.1.dist-info/top_level.txt
odoo14_addon_hr_personal_equipment_request_tier_validation-14.0.1.0.1.dist-info/RECORD
